twistor/__init__.py
twistor/bot.py
twistor-0.1.0.dist-info/METADATA
twistor-0.1.0.dist-info/WHEEL
twistor-0.1.0.dist-info/top_level.txt
twistor-0.1.0.dist-info/RECORD
