Metadata-Version: 2.1
Name: twistor
Version: 0.1.0
Summary: A language or a package used to make discord bots..... :)
Home-page: https://github.com/Siddhartha41210-git/Twistor
Author: Siddhartha41210
Author-email: cooldevsiddhartha41210@gmail.com
License: MIT
Classifier: Programming Language :: Python :: 3
Classifier: License :: OSI Approved :: MIT License
Classifier: Operating System :: OS Independent
Requires-Python: >=3.8
Requires-Dist: discord.py >=2.0.0
